aggarage/__init__.py
aggarage/__main__.py
aggarage/aggpt6m.py
aggarage/tests.py
aggarage/Clovis/Clovis.py
aggarage/Clovis/__init__.py
aggarage/Clovis/corpus.py
aggarage-0.4.5.dist-info/licenses/LICENSE
aggarage-0.4.5.dist-info/METADATA
aggarage-0.4.5.dist-info/WHEEL
aggarage-0.4.5.dist-info/top_level.txt
aggarage-0.4.5.dist-info/RECORD
